linear_model.py
sklearn_linear_model_modification.py
sklearn_linear_model_modification-0.0.11.dist-info/LICENSE.txt
sklearn_linear_model_modification-0.0.11.dist-info/METADATA
sklearn_linear_model_modification-0.0.11.dist-info/WHEEL
sklearn_linear_model_modification-0.0.11.dist-info/top_level.txt
sklearn_linear_model_modification-0.0.11.dist-info/RECORD
