Metadata-Version: 2.1
Name: sklearn-linear-model-modification
Version: 0.0.11
Summary: Wraps sklearn linear_model regression functions to allow Drop1, Add1, and VIF calculations
Home-page: https://github.com/chrisebell24/sklearn_linear_model_modification
Author: Christopher Bell
Author-email: Chris.E.Bell24@gmail.com
Maintainer: Christopher Bell
Maintainer-email: Chris.E.Bell24@gmail.com
License: UNKNOWN
Platform: UNKNOWN
Classifier: Programming Language :: Python :: 3
Classifier: Programming Language :: Python :: 3.6
Classifier: Programming Language :: Python :: 3.7
Classifier: License :: OSI Approved :: GNU General Public License v2 or later (GPLv2+)
Classifier: Operating System :: OS Independent
Requires-Dist: numpy (>=1.16.1)
Requires-Dist: pandas (>=1.0.0)
Requires-Dist: scikit-learn (>=0.20.0)
Requires-Dist: statsmodels (>=0.12.0)
Requires-Dist: scipy (>=1.3.0)
Provides-Extra: dev
Requires-Dist: pytest (>=3.7) ; extra == 'dev'
